{
  "BTCUSDT": {
    "5m": {
      "price": 110149.03,
      "volume": 17.42,
      "RSI": 50.42,
      "Stoch_K": 57.63,
      "Stoch_D": 64.65,
      "MACD": {
        "line": 8.03456455,
        "signal": 0.84866287,
        "histogram": 7.18590168
      },
      "EMA_50": 110186.659627,
      "EMA_200": 110479.804524,
      "Bollinger_Bands": {
        "upper": 110223.045188,
        "middle": 110125.013,
        "lower": 110026.980812,
        "bandwidth": 0.18
      },
      "Volume_SMA_20": 12.85,
      "ATR": 33.495,
      "Williams_R": -42.37,
      "CCI": 20.75,
      "ADX": {
        "adx": 20.09,
        "di_plus": 17.95,
        "di_minus": 26.97
      },
      "OBV": -432.42,
      "Support_Resistance": {
        "resistance": 110215.03,
        "support": 110034.44,
        "resistance_distance_pct": 0.06,
        "support_distance_pct": 0.1
      },
      "Parabolic_SAR": {
        "sar": 110215.03,
        "trend": -1,
        "is_bullish": false
      },
      "signal": "neutral",
      "signal_score": -1,
      "signal_details": [
        "MACD_bullish",
        "EMA_death_cross",
        "SAR_bearish"
      ]
    },
    "15m": {
      "price": 110149.03,
      "volume": 29.03,
      "RSI": 42.11,
      "Stoch_K": 52.17,
      "Stoch_D": 61.06,
      "MACD": {
        "line": -97.69714138,
        "signal": -126.84437588,
        "histogram": 29.1472345
      },
      "EMA_50": 110419.507081,
      "EMA_200": 110702.978709,
      "Bollinger_Bands": {
        "upper": 110286.168938,
        "middle": 110145.7155,
        "lower": 110005.262062,
        "bandwidth": 0.26
      },
      "Volume_SMA_20": 44.5,
      "ATR": 85.75071429,
      "Williams_R": -47.83,
      "CCI": -8.33,
      "ADX": {
        "adx": 36.13,
        "di_plus": 15.6,
        "di_minus": 33.24
      },
      "OBV": 1125.31,
      "Support_Resistance": {
        "resistance": 110303.2,
        "support": 110000,
        "resistance_distance_pct": 0.14,
        "support_distance_pct": 0.14
      },
      "Parabolic_SAR": {
        "sar": 110247.980059,
        "trend": -1,
        "is_bullish": false
      },
      "signal": "neutral",
      "signal_score": -2,
      "signal_details": [
        "MACD_bullish",
        "EMA_death_cross",
        "Strong_trend",
        "SAR_bearish"
      ]
    },
    "1h": {
      "price": 110149.03,
      "volume": 116.97,
      "RSI": 39.26,
      "Stoch_K": 16.82,
      "Stoch_D": 13.8,
      "MACD": {
        "line": -260.68681605,
        "signal": -210.84044081,
        "histogram": -49.84637524
      },
      "EMA_50": 110826.994043,
      "EMA_200": 110199.143695,
      "Bollinger_Bands": {
        "upper": 111318.908318,
        "middle": 110631.927,
        "lower": 109944.945682,
        "bandwidth": 1.24
      },
      "Volume_SMA_20": 211.17,
      "ATR": 227.69357143,
      "Williams_R": -83.18,
      "CCI": -107.54,
      "ADX": {
        "adx": 26.19,
        "di_plus": 16.79,
        "di_minus": 28.7
      },
      "OBV": 526.82,
      "Support_Resistance": {
        "resistance": 111307.7,
        "support": 109977,
        "resistance_distance_pct": 1.05,
        "support_distance_pct": 0.16
      },
      "Parabolic_SAR": {
        "sar": 110901.557309,
        "trend": -1,
        "is_bullish": false
      },
      "signal": "neutral",
      "signal_score": 1,
      "signal_details": [
        "Stoch_oversold",
        "MACD_bearish",
        "EMA_golden_cross",
        "WilliamsR_oversold",
        "Strong_trend",
        "SAR_bearish"
      ]
    },
    "4h": {
      "price": 110149.03,
      "volume": 257.06,
      "RSI": 46.01,
      "Stoch_K": 19.54,
      "Stoch_D": 21.01,
      "MACD": {
        "line": -19.58048465,
        "signal": 158.13394413,
        "histogram": -177.71442878
      },
      "EMA_50": 110775.05287,
      "EMA_200": 112924.383664,
      "Bollinger_Bands": {
        "upper": 112659.281404,
        "middle": 110961.741,
        "lower": 109264.200596,
        "bandwidth": 3.06
      },
      "Volume_SMA_20": 2067.05,
      "ATR": 1082.26642857,
      "Williams_R": -80.46,
      "CCI": -101.48,
      "ADX": {
        "adx": 18.55,
        "di_plus": 15.68,
        "di_minus": 22.82
      },
      "OBV": -37831.66,
      "Support_Resistance": {
        "resistance": 113384.62,
        "support": 109329.12,
        "resistance_distance_pct": 2.94,
        "support_distance_pct": 0.74
      },
      "Parabolic_SAR": {
        "sar": 113316.4676,
        "trend": -1,
        "is_bullish": false
      },
      "signal": "neutral",
      "signal_score": -2,
      "signal_details": [
        "MACD_bearish",
        "EMA_death_cross",
        "WilliamsR_oversold",
        "SAR_bearish",
        "Low_volume"
      ]
    }
  },
  "ETHUSDT": {
    "5m": {
      "price": 4270.14,
      "volume": 739.18,
      "RSI": 47.8,
      "Stoch_K": 36.74,
      "Stoch_D": 60.67,
      "MACD": {
        "line": 1.50133787,
        "signal": 1.23393299,
        "histogram": 0.26740488
      },
      "EMA_50": 4272.572933,
      "EMA_200": 4285.581672,
      "Bollinger_Bands": {
        "upper": 4283.011537,
        "middle": 4270.7055,
        "lower": 4258.399463,
        "bandwidth": 0.58
      },
      "Volume_SMA_20": 416.31,
      "ATR": 3.97142857,
      "Williams_R": -63.26,
      "CCI": 21.37,
      "ADX": {
        "adx": 2.89,
        "di_plus": 21.68,
        "di_minus": 22.97
      },
      "OBV": -17872.13,
      "Support_Resistance": {
        "resistance": 4280.59,
        "support": 4253.35,
        "resistance_distance_pct": 0.24,
        "support_distance_pct": 0.39
      },
      "Parabolic_SAR": {
        "sar": 4280.59,
        "trend": -1,
        "is_bullish": false
      },
      "signal": "neutral",
      "signal_score": 0,
      "signal_details": [
        "MACD_bullish",
        "EMA_death_cross",
        "SAR_bearish",
        "High_volume"
      ]
    },
    "15m": {
      "price": 4270.14,
      "volume": 1079.94,
      "RSI": 46.39,
      "Stoch_K": 57.89,
      "Stoch_D": 61.6,
      "MACD": {
        "line": -3.64617588,
        "signal": -5.07072105,
        "histogram": 1.42454517
      },
      "EMA_50": 4282.734089,
      "EMA_200": 4302.539955,
      "Bollinger_Bands": {
        "upper": 4290.235433,
        "middle": 4272.8885,
        "lower": 4255.541567,
        "bandwidth": 0.81
      },
      "Volume_SMA_20": 2026.64,
      "ATR": 8.36642857,
      "Williams_R": -42.11,
      "CCI": -10.59,
      "ADX": {
        "adx": 11.24,
        "di_plus": 21.7,
        "di_minus": 27.19
      },
      "OBV": -120545.37,
      "Support_Resistance": {
        "resistance": 4304.25,
        "support": 4251.24,
        "resistance_distance_pct": 0.8,
        "support_distance_pct": 0.44
      },
      "Parabolic_SAR": {
        "sar": 4256.333159,
        "trend": 1,
        "is_bullish": true
      },
      "signal": "neutral",
      "signal_score": 1,
      "signal_details": [
        "MACD_bullish",
        "EMA_death_cross",
        "SAR_bullish"
      ]
    },
    "1h": {
      "price": 4270.13,
      "volume": 2451.34,
      "RSI": 42.34,
      "Stoch_K": 43.18,
      "Stoch_D": 40.76,
      "MACD": {
        "line": -15.27659693,
        "signal": -14.15592735,
        "histogram": -1.12066958
      },
      "EMA_50": 4316.229372,
      "EMA_200": 4342.378671,
      "Bollinger_Bands": {
        "upper": 4328.613218,
        "middle": 4293.696,
        "lower": 4258.778782,
        "bandwidth": 1.63
      },
      "Volume_SMA_20": 7895.15,
      "ATR": 22.23714286,
      "Williams_R": -56.82,
      "CCI": -99.57,
      "ADX": {
        "adx": 52.75,
        "di_plus": 8.96,
        "di_minus": 28.98
      },
      "OBV": 23882.06,
      "Support_Resistance": {
        "resistance": 4325,
        "support": 4236,
        "resistance_distance_pct": 1.28,
        "support_distance_pct": 0.8
      },
      "Parabolic_SAR": {
        "sar": 4311.38551,
        "trend": -1,
        "is_bullish": false
      },
      "signal": "sell",
      "signal_score": -4,
      "signal_details": [
        "MACD_bearish",
        "EMA_death_cross",
        "Strong_trend",
        "SAR_bearish",
        "Low_volume"
      ]
    },
    "4h": {
      "price": 4270.13,
      "volume": 8326.19,
      "RSI": 42.71,
      "Stoch_K": 13.44,
      "Stoch_D": 9.06,
      "MACD": {
        "line": -29.11249326,
        "signal": -22.32602308,
        "histogram": -6.78647018
      },
      "EMA_50": 4368.490804,
      "EMA_200": 4292.904639,
      "Bollinger_Bands": {
        "upper": 4468.220178,
        "middle": 4339.757,
        "lower": 4211.293822,
        "bandwidth": 5.92
      },
      "Volume_SMA_20": 70689.78,
      "ATR": 66.08,
      "Williams_R": -86.56,
      "CCI": -98.93,
      "ADX": {
        "adx": 28.87,
        "di_plus": 13.73,
        "di_minus": 24.87
      },
      "OBV": 1868791.03,
      "Support_Resistance": {
        "resistance": 4490.64,
        "support": 4236,
        "resistance_distance_pct": 5.16,
        "support_distance_pct": 0.8
      },
      "Parabolic_SAR": {
        "sar": 4475.485248,
        "trend": -1,
        "is_bullish": false
      },
      "signal": "neutral",
      "signal_score": 1,
      "signal_details": [
        "Stoch_oversold",
        "MACD_bearish",
        "EMA_golden_cross",
        "WilliamsR_oversold",
        "Strong_trend",
        "SAR_bearish",
        "Low_volume"
      ]
    }
  },
  "updated_at": "2025-09-06T21:38:46Z"
}
