{
  "BTCUSDT": {
    "5m": {
      "price": 77026.03,
      "volume": 23.53,
      "RSI": 71.59,
      "Stoch_K": 96.36,
      "Stoch_D": 93.33,
      "MACD": {
        "line": 130.30709824,
        "signal": 91.40194132,
        "histogram": 38.90515693
      },
      "EMA_50": 76646.569066,
      "EMA_200": 76767.701653,
      "Bollinger_Bands": {
        "upper": 77171.968981,
        "middle": 76666.568,
        "lower": 76161.167019,
        "bandwidth": 1.32
      },
      "Volume_SMA_20": 55.42,
      "ATR": 124.51714286,
      "Williams_R": -3.64,
      "CCI": 117.69,
      "ADX": {
        "adx": 43.39,
        "di_plus": 35.85,
        "di_minus": 14.16
      },
      "OBV": -670.22,
      "Support_Resistance": {
        "resistance": 77044,
        "support": 76211.55,
        "resistance_distance_pct": 0.02,
        "support_distance_pct": 1.06
      },
      "Parabolic_SAR": {
        "sar": 76543.182214,
        "trend": 1,
        "is_bullish": true
      },
      "signal": "sell",
      "signal_score": -3,
      "signal_details": [
        "RSI_overbought",
        "Stoch_overbought",
        "MACD_bullish",
        "EMA_death_cross",
        "WilliamsR_overbought",
        "Strong_trend",
        "SAR_bullish",
        "Low_volume"
      ]
    },
    "15m": {
      "price": 77026.03,
      "volume": 99.52,
      "RSI": 60.5,
      "Stoch_K": 98,
      "Stoch_D": 95.83,
      "MACD": {
        "line": 15.2280668,
        "signal": -67.29031819,
        "histogram": 82.51838499
      },
      "EMA_50": 76784.609674,
      "EMA_200": 77423.807347,
      "Bollinger_Bands": {
        "upper": 77001.699448,
        "middle": 76528.047,
        "lower": 76054.394552,
        "bandwidth": 1.24
      },
      "Volume_SMA_20": 226.61,
      "ATR": 226.82857143,
      "Williams_R": -2,
      "CCI": 173.32,
      "ADX": {
        "adx": 22.24,
        "di_plus": 28.65,
        "di_minus": 18.23
      },
      "OBV": -5536.44,
      "Support_Resistance": {
        "resistance": 77044,
        "support": 76051,
        "resistance_distance_pct": 0.02,
        "support_distance_pct": 1.27
      },
      "Parabolic_SAR": {
        "sar": 76252.217195,
        "trend": 1,
        "is_bullish": true
      },
      "signal": "sell",
      "signal_score": -3,
      "signal_details": [
        "Stoch_overbought",
        "MACD_bullish",
        "EMA_death_cross",
        "BB_overbought",
        "WilliamsR_overbought",
        "SAR_bullish",
        "Low_volume"
      ]
    },
    "1h": {
      "price": 77026.02,
      "volume": 99.52,
      "RSI": 48.52,
      "Stoch_K": 55.75,
      "Stoch_D": 39.14,
      "MACD": {
        "line": -280.50822685,
        "signal": -319.02009853,
        "histogram": 38.51187168
      },
      "EMA_50": 77554.951807,
      "EMA_200": 79162.96466,
      "Bollinger_Bands": {
        "upper": 77515.870183,
        "middle": 76877.662,
        "lower": 76239.453817,
        "bandwidth": 1.66
      },
      "Volume_SMA_20": 809.59,
      "ATR": 479.49642857,
      "Williams_R": -44.25,
      "CCI": 36.53,
      "ADX": {
        "adx": 15.68,
        "di_plus": 19.62,
        "di_minus": 26.92
      },
      "OBV": -8872.52,
      "Support_Resistance": {
        "resistance": 77800,
        "support": 76051,
        "resistance_distance_pct": 1,
        "support_distance_pct": 1.27
      },
      "Parabolic_SAR": {
        "sar": 77451.484472,
        "trend": -1,
        "is_bullish": false
      },
      "signal": "neutral",
      "signal_score": -1,
      "signal_details": [
        "MACD_bullish",
        "EMA_death_cross",
        "SAR_bearish",
        "Low_volume"
      ]
    },
    "4h": {
      "price": 77026.02,
      "volume": 99.52,
      "RSI": 37.53,
      "Stoch_K": 38.25,
      "Stoch_D": 28.91,
      "MACD": {
        "line": -779.91644354,
        "signal": -718.18761536,
        "histogram": -61.72882818
      },
      "EMA_50": 78945.756076,
      "EMA_200": 78428.950172,
      "Bollinger_Bands": {
        "upper": 79464.95315,
        "middle": 77931.883,
        "lower": 76398.81285,
        "bandwidth": 3.93
      },
      "Volume_SMA_20": 2086.09,
      "ATR": 692.17,
      "Williams_R": -61.75,
      "CCI": -97.95,
      "ADX": {
        "adx": 49.78,
        "di_plus": 9.39,
        "di_minus": 28.01
      },
      "OBV": 16262.24,
      "Support_Resistance": {
        "resistance": 79561.94,
        "support": 76051,
        "resistance_distance_pct": 3.29,
        "support_distance_pct": 1.27
      },
      "Parabolic_SAR": {
        "sar": 78045.118373,
        "trend": -1,
        "is_bullish": false
      },
      "signal": "neutral",
      "signal_score": -2,
      "signal_details": [
        "MACD_bearish",
        "EMA_golden_cross",
        "Strong_trend",
        "SAR_bearish",
        "Low_volume"
      ]
    }
  },
  "ETHUSDT": {
    "5m": {
      "price": 2125.49,
      "volume": 528.18,
      "RSI": 72.1,
      "Stoch_K": 86.69,
      "Stoch_D": 88.84,
      "MACD": {
        "line": 6.90456913,
        "signal": 4.43456601,
        "histogram": 2.47000311
      },
      "EMA_50": 2108.221316,
      "EMA_200": 2114.365003,
      "Bollinger_Bands": {
        "upper": 2136.502046,
        "middle": 2106.8635,
        "lower": 2077.224954,
        "bandwidth": 2.81
      },
      "Volume_SMA_20": 2211.53,
      "ATR": 6.12642857,
      "Williams_R": -13.31,
      "CCI": 108.95,
      "ADX": {
        "adx": 42.83,
        "di_plus": 33.66,
        "di_minus": 13.47
      },
      "OBV": -14966.66,
      "Support_Resistance": {
        "resistance": 2129.84,
        "support": 2079.64,
        "resistance_distance_pct": 0.2,
        "support_distance_pct": 2.16
      },
      "Parabolic_SAR": {
        "sar": 2099.955298,
        "trend": 1,
        "is_bullish": true
      },
      "signal": "sell",
      "signal_score": -3,
      "signal_details": [
        "RSI_overbought",
        "Stoch_overbought",
        "MACD_bullish",
        "EMA_death_cross",
        "WilliamsR_overbought",
        "Strong_trend",
        "SAR_bullish",
        "Low_volume"
      ]
    },
    "15m": {
      "price": 2125.49,
      "volume": 3233.45,
      "RSI": 60,
      "Stoch_K": 91.73,
      "Stoch_D": 94.47,
      "MACD": {
        "line": -0.62322801,
        "signal": -4.54335465,
        "histogram": 3.92012664
      },
      "EMA_50": 2115.360992,
      "EMA_200": 2145.464358,
      "Bollinger_Bands": {
        "upper": 2125.527357,
        "middle": 2103.5515,
        "lower": 2081.575643,
        "bandwidth": 2.09
      },
      "Volume_SMA_20": 5783.48,
      "ATR": 11.02285714,
      "Williams_R": -8.27,
      "CCI": 207.57,
      "ADX": {
        "adx": 10.92,
        "di_plus": 29.47,
        "di_minus": 23.67
      },
      "OBV": -113316.8,
      "Support_Resistance": {
        "resistance": 2129.84,
        "support": 2077.23,
        "resistance_distance_pct": 0.2,
        "support_distance_pct": 2.27
      },
      "Parabolic_SAR": {
        "sar": 2083.110881,
        "trend": 1,
        "is_bullish": true
      },
      "signal": "neutral",
      "signal_score": -2,
      "signal_details": [
        "Stoch_overbought",
        "MACD_bullish",
        "EMA_death_cross",
        "WilliamsR_overbought",
        "SAR_bullish"
      ]
    },
    "1h": {
      "price": 2125.66,
      "volume": 3260.07,
      "RSI": 48.26,
      "Stoch_K": 60.53,
      "Stoch_D": 41.81,
      "MACD": {
        "line": -13.12844103,
        "signal": -15.05281671,
        "histogram": 1.92437568
      },
      "EMA_50": 2150.897746,
      "EMA_200": 2227.109725,
      "Bollinger_Bands": {
        "upper": 2145.30106,
        "middle": 2118.008,
        "lower": 2090.71494,
        "bandwidth": 2.58
      },
      "Volume_SMA_20": 15452.68,
      "ATR": 20.47785714,
      "Williams_R": -39.47,
      "CCI": 70.78,
      "ADX": {
        "adx": 22.1,
        "di_plus": 17.47,
        "di_minus": 27.38
      },
      "OBV": -226373.15,
      "Support_Resistance": {
        "resistance": 2157.24,
        "support": 2077.23,
        "resistance_distance_pct": 1.49,
        "support_distance_pct": 2.28
      },
      "Parabolic_SAR": {
        "sar": 2142.273925,
        "trend": -1,
        "is_bullish": false
      },
      "signal": "neutral",
      "signal_score": -1,
      "signal_details": [
        "MACD_bullish",
        "EMA_death_cross",
        "SAR_bearish",
        "Low_volume"
      ]
    },
    "4h": {
      "price": 2125.66,
      "volume": 3260.07,
      "RSI": 32.75,
      "Stoch_K": 40.05,
      "Stoch_D": 31.54,
      "MACD": {
        "line": -35.81390042,
        "signal": -33.47191183,
        "histogram": -2.3419886
      },
      "EMA_50": 2221.976429,
      "EMA_200": 2295.678472,
      "Bollinger_Bands": {
        "upper": 2243.782906,
        "middle": 2169.451,
        "lower": 2095.119094,
        "bandwidth": 6.85
      },
      "Volume_SMA_20": 38454.43,
      "ATR": 28.51142857,
      "Williams_R": -59.95,
      "CCI": -88.65,
      "ADX": {
        "adx": 47.12,
        "di_plus": 11.56,
        "di_minus": 32.16
      },
      "OBV": -99073.67,
      "Support_Resistance": {
        "resistance": 2232.88,
        "support": 2077.23,
        "resistance_distance_pct": 5.04,
        "support_distance_pct": 2.28
      },
      "Parabolic_SAR": {
        "sar": 2158.544653,
        "trend": -1,
        "is_bullish": false
      },
      "signal": "sell",
      "signal_score": -4,
      "signal_details": [
        "MACD_bearish",
        "EMA_death_cross",
        "Strong_trend",
        "SAR_bearish",
        "Low_volume"
      ]
    }
  },
  "updated_at": "2026-05-18T20:12:49Z"
}
