{
  "BTCUSDT": {
    "5m": {
      "price": 87829.07,
      "volume": 12.59,
      "RSI": 62.46,
      "Stoch_K": 57.35,
      "Stoch_D": 57.46,
      "MACD": {
        "line": 256.84637691,
        "signal": 234.51209558,
        "histogram": 22.33428133
      },
      "EMA_50": 87126.977988,
      "EMA_200": 86721.725022,
      "Bollinger_Bands": {
        "upper": 88308.267356,
        "middle": 87452.4245,
        "lower": 86596.581644,
        "bandwidth": 1.96
      },
      "Volume_SMA_20": 102.06,
      "ATR": 221.97857143,
      "Williams_R": -42.65,
      "CCI": 64.05,
      "ADX": {
        "adx": 51.87,
        "di_plus": 34.5,
        "di_minus": 10.93
      },
      "OBV": 146.06,
      "Support_Resistance": {
        "resistance": 88449.06,
        "support": 86907.8,
        "resistance_distance_pct": 0.71,
        "support_distance_pct": 1.05
      },
      "Parabolic_SAR": {
        "sar": 87660.457935,
        "trend": 1,
        "is_bullish": true
      },
      "signal": "buy",
      "signal_score": 4,
      "signal_details": [
        "MACD_bullish",
        "EMA_golden_cross",
        "Strong_trend",
        "SAR_bullish",
        "Low_volume"
      ]
    },
    "15m": {
      "price": 87829.06,
      "volume": 154.72,
      "RSI": 66.17,
      "Stoch_K": 65.59,
      "Stoch_D": 73.55,
      "MACD": {
        "line": 467.78001943,
        "signal": 392.35550154,
        "histogram": 75.4245179
      },
      "EMA_50": 86612.992521,
      "EMA_200": 86602.000117,
      "Bollinger_Bands": {
        "upper": 88143.393764,
        "middle": 87098.06,
        "lower": 86052.726236,
        "bandwidth": 2.4
      },
      "Volume_SMA_20": 291.07,
      "ATR": 321.99714286,
      "Williams_R": -34.41,
      "CCI": 158.11,
      "ADX": {
        "adx": 56.28,
        "di_plus": 37.88,
        "di_minus": 10.6
      },
      "OBV": 798.48,
      "Support_Resistance": {
        "resistance": 88449.06,
        "support": 85564,
        "resistance_distance_pct": 0.71,
        "support_distance_pct": 2.58
      },
      "Parabolic_SAR": {
        "sar": 86804.169704,
        "trend": 1,
        "is_bullish": true
      },
      "signal": "buy",
      "signal_score": 4,
      "signal_details": [
        "MACD_bullish",
        "EMA_golden_cross",
        "Strong_trend",
        "SAR_bullish"
      ]
    },
    "1h": {
      "price": 87829.06,
      "volume": 1649.87,
      "RSI": 60.95,
      "Stoch_K": 84.5,
      "Stoch_D": 78.42,
      "MACD": {
        "line": 91.42811508,
        "signal": -137.76803585,
        "histogram": 229.19615093
      },
      "EMA_50": 86762.993323,
      "EMA_200": 88293.936056,
      "Bollinger_Bands": {
        "upper": 89172.938083,
        "middle": 86612.5235,
        "lower": 84052.108917,
        "bandwidth": 5.91
      },
      "Volume_SMA_20": 1355.91,
      "ATR": 840.86714286,
      "Williams_R": -15.5,
      "CCI": 79.88,
      "ADX": {
        "adx": 33.6,
        "di_plus": 33.58,
        "di_minus": 16.69
      },
      "OBV": -7670.59,
      "Support_Resistance": {
        "resistance": 89477.61,
        "support": 84450.01,
        "resistance_distance_pct": 1.88,
        "support_distance_pct": 3.85
      },
      "Parabolic_SAR": {
        "sar": 84692.142156,
        "trend": 1,
        "is_bullish": true
      },
      "signal": "neutral",
      "signal_score": 1,
      "signal_details": [
        "MACD_bullish",
        "EMA_death_cross",
        "WilliamsR_overbought",
        "Strong_trend",
        "SAR_bullish"
      ]
    },
    "4h": {
      "price": 87829.06,
      "volume": 3563.18,
      "RSI": 51.9,
      "Stoch_K": 57.12,
      "Stoch_D": 38.8,
      "MACD": {
        "line": -521.64997956,
        "signal": -674.87346314,
        "histogram": 153.22348358
      },
      "EMA_50": 88246.22529,
      "EMA_200": 90294.978053,
      "Bollinger_Bands": {
        "upper": 88730.755378,
        "middle": 86865.507,
        "lower": 85000.258622,
        "bandwidth": 4.29
      },
      "Volume_SMA_20": 3528.52,
      "ATR": 1716.445,
      "Williams_R": -42.88,
      "CCI": 79.24,
      "ADX": {
        "adx": 17.51,
        "di_plus": 32.1,
        "di_minus": 22.53
      },
      "OBV": -31288.23,
      "Support_Resistance": {
        "resistance": 90365.85,
        "support": 84450.01,
        "resistance_distance_pct": 2.89,
        "support_distance_pct": 3.85
      },
      "Parabolic_SAR": {
        "sar": 89057.538477,
        "trend": -1,
        "is_bullish": false
      },
      "signal": "neutral",
      "signal_score": -1,
      "signal_details": [
        "MACD_bullish",
        "EMA_death_cross",
        "SAR_bearish"
      ]
    }
  },
  "ETHUSDT": {
    "5m": {
      "price": 2952.57,
      "volume": 531.75,
      "RSI": 61.33,
      "Stoch_K": 49.74,
      "Stoch_D": 49.99,
      "MACD": {
        "line": 10.79734542,
        "signal": 10.84506654,
        "histogram": -0.04772112
      },
      "EMA_50": 2921.807096,
      "EMA_200": 2890.002861,
      "Bollinger_Bands": {
        "upper": 2976.595896,
        "middle": 2940.0095,
        "lower": 2903.423104,
        "bandwidth": 2.49
      },
      "Volume_SMA_20": 2298.82,
      "ATR": 10.66357143,
      "Williams_R": -50.26,
      "CCI": 50.32,
      "ADX": {
        "adx": 23.36,
        "di_plus": 32.01,
        "di_minus": 19.88
      },
      "OBV": -43294.02,
      "Support_Resistance": {
        "resistance": 2984.33,
        "support": 2915.98,
        "resistance_distance_pct": 1.08,
        "support_distance_pct": 1.24
      },
      "Parabolic_SAR": {
        "sar": 2982.685412,
        "trend": -1,
        "is_bullish": false
      },
      "signal": "neutral",
      "signal_score": -1,
      "signal_details": [
        "MACD_bearish",
        "EMA_golden_cross",
        "SAR_bearish",
        "Low_volume"
      ]
    },
    "15m": {
      "price": 2952.57,
      "volume": 7043.31,
      "RSI": 69.67,
      "Stoch_K": 57.37,
      "Stoch_D": 66.83,
      "MACD": {
        "line": 26.24728833,
        "signal": 24.29038067,
        "histogram": 1.95690765
      },
      "EMA_50": 2886.014454,
      "EMA_200": 2877.525327,
      "Bollinger_Bands": {
        "upper": 2976.417348,
        "middle": 2920.1795,
        "lower": 2863.941652,
        "bandwidth": 3.85
      },
      "Volume_SMA_20": 9349.83,
      "ATR": 14.65928571,
      "Williams_R": -42.63,
      "CCI": 117.41,
      "ADX": {
        "adx": 54.25,
        "di_plus": 36.26,
        "di_minus": 10.75
      },
      "OBV": 16799.01,
      "Support_Resistance": {
        "resistance": 2984.33,
        "support": 2830.55,
        "resistance_distance_pct": 1.08,
        "support_distance_pct": 4.13
      },
      "Parabolic_SAR": {
        "sar": 2929.772777,
        "trend": 1,
        "is_bullish": true
      },
      "signal": "buy",
      "signal_score": 4,
      "signal_details": [
        "MACD_bullish",
        "EMA_golden_cross",
        "Strong_trend",
        "SAR_bullish"
      ]
    },
    "1h": {
      "price": 2952.57,
      "volume": 34159.53,
      "RSI": 64.75,
      "Stoch_K": 84.81,
      "Stoch_D": 86.79,
      "MACD": {
        "line": 14.8623316,
        "signal": 0.7016639,
        "histogram": 14.16066769
      },
      "EMA_50": 2886.621318,
      "EMA_200": 3013.309948,
      "Bollinger_Bands": {
        "upper": 3001.672101,
        "middle": 2877.9995,
        "lower": 2754.326899,
        "bandwidth": 8.59
      },
      "Volume_SMA_20": 36215.35,
      "ATR": 37.77357143,
      "Williams_R": -15.19,
      "CCI": 101.4,
      "ADX": {
        "adx": 38.28,
        "di_plus": 35.17,
        "di_minus": 15.7
      },
      "OBV": -461561.1,
      "Support_Resistance": {
        "resistance": 2997.4,
        "support": 2775.19,
        "resistance_distance_pct": 1.52,
        "support_distance_pct": 6.01
      },
      "Parabolic_SAR": {
        "sar": 2800.361313,
        "trend": 1,
        "is_bullish": true
      },
      "signal": "neutral",
      "signal_score": -1,
      "signal_details": [
        "Stoch_overbought",
        "MACD_bullish",
        "EMA_death_cross",
        "WilliamsR_overbought",
        "Strong_trend",
        "SAR_bullish"
      ]
    },
    "4h": {
      "price": 2952.57,
      "volume": 91263.82,
      "RSI": 51.18,
      "Stoch_K": 69.36,
      "Stoch_D": 47.52,
      "MACD": {
        "line": -43.83538576,
        "signal": -55.68589022,
        "histogram": 11.85050446
      },
      "EMA_50": 2994.382168,
      "EMA_200": 3055.251329,
      "Bollinger_Bands": {
        "upper": 3018.40764,
        "middle": 2901.898,
        "lower": 2785.38836,
        "bandwidth": 8.03
      },
      "Volume_SMA_20": 84316.98,
      "ATR": 79.18928571,
      "Williams_R": -30.64,
      "CCI": 64.29,
      "ADX": {
        "adx": 19.74,
        "di_plus": 31.4,
        "di_minus": 21.05
      },
      "OBV": 6722.1,
      "Support_Resistance": {
        "resistance": 3030.92,
        "support": 2775.19,
        "resistance_distance_pct": 2.65,
        "support_distance_pct": 6.01
      },
      "Parabolic_SAR": {
        "sar": 2988.600484,
        "trend": -1,
        "is_bullish": false
      },
      "signal": "neutral",
      "signal_score": -1,
      "signal_details": [
        "MACD_bullish",
        "EMA_death_cross",
        "SAR_bearish"
      ]
    }
  },
  "updated_at": "2025-12-19T07:42:05Z"
}
