{
  "BTCUSDT": {
    "5m": {
      "price": 105364.89,
      "volume": 18.25,
      "RSI": 46.08,
      "Stoch_K": 63.97,
      "Stoch_D": 71.4,
      "MACD": {
        "line": -245.73267461,
        "signal": -377.32725689,
        "histogram": 131.59458227
      },
      "EMA_50": 106147.934083,
      "EMA_200": 107606.2323,
      "Bollinger_Bands": {
        "upper": 105559.599237,
        "middle": 105153.36,
        "lower": 104747.120763,
        "bandwidth": 0.77
      },
      "Volume_SMA_20": 271.27,
      "ATR": 293.22785714,
      "Williams_R": -36.03,
      "CCI": 104.22,
      "ADX": {
        "adx": 2.85,
        "di_plus": 21.33,
        "di_minus": 22.58
      },
      "OBV": -6312.11,
      "Support_Resistance": {
        "resistance": 105716.15,
        "support": 104505,
        "resistance_distance_pct": 0.33,
        "support_distance_pct": 0.82
      },
      "Parabolic_SAR": {
        "sar": 105667.683387,
        "trend": -1,
        "is_bullish": false
      },
      "signal": "neutral",
      "signal_score": -1,
      "signal_details": [
        "MACD_bullish",
        "EMA_death_cross",
        "SAR_bearish",
        "Low_volume"
      ]
    },
    "15m": {
      "price": 105364.89,
      "volume": 281.86,
      "RSI": 27.91,
      "Stoch_K": 22.42,
      "Stoch_D": 18.5,
      "MACD": {
        "line": -916.40187007,
        "signal": -809.09349311,
        "histogram": -107.30837696
      },
      "EMA_50": 107482.263987,
      "EMA_200": 109628.222094,
      "Bollinger_Bands": {
        "upper": 109597.337837,
        "middle": 106660.6235,
        "lower": 103723.909163,
        "bandwidth": 5.51
      },
      "Volume_SMA_20": 675,
      "ATR": 620.61571429,
      "Williams_R": -77.58,
      "CCI": -67.53,
      "ADX": {
        "adx": 50.67,
        "di_plus": 11.33,
        "di_minus": 34.62
      },
      "OBV": -8681.47,
      "Support_Resistance": {
        "resistance": 109011.01,
        "support": 104505,
        "resistance_distance_pct": 3.46,
        "support_distance_pct": 0.82
      },
      "Parabolic_SAR": {
        "sar": 104505,
        "trend": 1,
        "is_bullish": true
      },
      "signal": "neutral",
      "signal_score": 0,
      "signal_details": [
        "RSI_oversold",
        "MACD_bearish",
        "EMA_death_cross",
        "Strong_trend",
        "SAR_bullish",
        "Low_volume"
      ]
    },
    "1h": {
      "price": 105364.89,
      "volume": 1171.74,
      "RSI": 28.69,
      "Stoch_K": 18.16,
      "Stoch_D": 9.55,
      "MACD": {
        "line": -1182.67248206,
        "signal": -880.70576468,
        "histogram": -301.96671738
      },
      "EMA_50": 109604.708437,
      "EMA_200": 113464.300591,
      "Bollinger_Bands": {
        "upper": 110794.718575,
        "middle": 108064.962,
        "lower": 105335.205425,
        "bandwidth": 5.05
      },
      "Volume_SMA_20": 1641.73,
      "ATR": 868.66642857,
      "Williams_R": -81.84,
      "CCI": -208.25,
      "ADX": {
        "adx": 72.77,
        "di_plus": 6.52,
        "di_minus": 41.4
      },
      "OBV": -60057.81,
      "Support_Resistance": {
        "resistance": 111420.02,
        "support": 104505,
        "resistance_distance_pct": 5.75,
        "support_distance_pct": 0.82
      },
      "Parabolic_SAR": {
        "sar": 108766.401429,
        "trend": -1,
        "is_bullish": false
      },
      "signal": "neutral",
      "signal_score": 1,
      "signal_details": [
        "RSI_oversold",
        "Stoch_oversold",
        "MACD_bearish",
        "EMA_death_cross",
        "WilliamsR_oversold",
        "Strong_trend",
        "SAR_bearish"
      ]
    },
    "4h": {
      "price": 105364.88,
      "volume": 5805.22,
      "RSI": 28.42,
      "Stoch_K": 9.54,
      "Stoch_D": 12.99,
      "MACD": {
        "line": -1972.77866353,
        "signal": -1543.81429959,
        "histogram": -428.96436394
      },
      "EMA_50": 113031.992076,
      "EMA_200": 115526.226423,
      "Bollinger_Bands": {
        "upper": 114847.615353,
        "middle": 110468.156,
        "lower": 106088.696647,
        "bandwidth": 7.93
      },
      "Volume_SMA_20": 4875.02,
      "ATR": 1746.45214286,
      "Williams_R": -90.46,
      "CCI": -216.25,
      "ADX": {
        "adx": 58.48,
        "di_plus": 9.15,
        "di_minus": 34.94
      },
      "OBV": -89759.52,
      "Support_Resistance": {
        "resistance": 113691,
        "support": 104505,
        "resistance_distance_pct": 7.9,
        "support_distance_pct": 0.82
      },
      "Parabolic_SAR": {
        "sar": 110533.233287,
        "trend": -1,
        "is_bullish": false
      },
      "signal": "neutral",
      "signal_score": 2,
      "signal_details": [
        "RSI_oversold",
        "Stoch_oversold",
        "MACD_bearish",
        "EMA_death_cross",
        "BB_oversold",
        "WilliamsR_oversold",
        "Strong_trend",
        "SAR_bearish"
      ]
    }
  },
  "ETHUSDT": {
    "5m": {
      "price": 3756.48,
      "volume": 435.25,
      "RSI": 50.82,
      "Stoch_K": 82.65,
      "Stoch_D": 89.92,
      "MACD": {
        "line": -9.77847308,
        "signal": -18.57591741,
        "histogram": 8.79744433
      },
      "EMA_50": 3784.738721,
      "EMA_200": 3862.046484,
      "Bollinger_Bands": {
        "upper": 3766.933458,
        "middle": 3734.517,
        "lower": 3702.100542,
        "bandwidth": 1.74
      },
      "Volume_SMA_20": 7766.6,
      "ATR": 16.84857143,
      "Williams_R": -17.35,
      "CCI": 128.21,
      "ADX": {
        "adx": 4.88,
        "di_plus": 22.37,
        "di_minus": 20.29
      },
      "OBV": -52697.9,
      "Support_Resistance": {
        "resistance": 3770,
        "support": 3696.74,
        "resistance_distance_pct": 0.36,
        "support_distance_pct": 1.59
      },
      "Parabolic_SAR": {
        "sar": 3704.472411,
        "trend": 1,
        "is_bullish": true
      },
      "signal": "neutral",
      "signal_score": -2,
      "signal_details": [
        "Stoch_overbought",
        "MACD_bullish",
        "EMA_death_cross",
        "WilliamsR_overbought",
        "SAR_bullish",
        "Low_volume"
      ]
    },
    "15m": {
      "price": 3756.48,
      "volume": 16194.08,
      "RSI": 33.56,
      "Stoch_K": 29.46,
      "Stoch_D": 23.51,
      "MACD": {
        "line": -45.08433752,
        "signal": -40.86868713,
        "histogram": -4.21565039
      },
      "EMA_50": 3851.161543,
      "EMA_200": 3956.332796,
      "Bollinger_Bands": {
        "upper": 3955.574581,
        "middle": 3809.517,
        "lower": 3663.459419,
        "bandwidth": 7.67
      },
      "Volume_SMA_20": 16256.27,
      "ATR": 34.75857143,
      "Williams_R": -70.54,
      "CCI": -56.2,
      "ADX": {
        "adx": 35.47,
        "di_plus": 15.95,
        "di_minus": 33.48
      },
      "OBV": -256830.37,
      "Support_Resistance": {
        "resistance": 3923.46,
        "support": 3696.74,
        "resistance_distance_pct": 4.45,
        "support_distance_pct": 1.59
      },
      "Parabolic_SAR": {
        "sar": 3696.74,
        "trend": 1,
        "is_bullish": true
      },
      "signal": "neutral",
      "signal_score": -2,
      "signal_details": [
        "MACD_bearish",
        "EMA_death_cross",
        "Strong_trend",
        "SAR_bullish"
      ]
    },
    "1h": {
      "price": 3756.17,
      "volume": 49301.22,
      "RSI": 33.03,
      "Stoch_K": 23.42,
      "Stoch_D": 9.04,
      "MACD": {
        "line": -56.56397118,
        "signal": -40.99211143,
        "histogram": -15.57185976
      },
      "EMA_50": 3947.485152,
      "EMA_200": 4074.34332,
      "Bollinger_Bands": {
        "upper": 4025.21084,
        "middle": 3881.428,
        "lower": 3737.64516,
        "bandwidth": 7.41
      },
      "Volume_SMA_20": 37113.96,
      "ATR": 47.02714286,
      "Williams_R": -76.58,
      "CCI": -187.82,
      "ADX": {
        "adx": 64.53,
        "di_plus": 8.55,
        "di_minus": 39.65
      },
      "OBV": -389040.94,
      "Support_Resistance": {
        "resistance": 4059.35,
        "support": 3696.74,
        "resistance_distance_pct": 8.07,
        "support_distance_pct": 1.58
      },
      "Parabolic_SAR": {
        "sar": 3877.9042,
        "trend": -1,
        "is_bullish": false
      },
      "signal": "sell",
      "signal_score": -4,
      "signal_details": [
        "MACD_bearish",
        "EMA_death_cross",
        "Strong_trend",
        "SAR_bearish"
      ]
    },
    "4h": {
      "price": 3756.17,
      "volume": 167927.32,
      "RSI": 34.28,
      "Stoch_K": 11.41,
      "Stoch_D": 13.19,
      "MACD": {
        "line": -71.88696115,
        "signal": -46.71125405,
        "histogram": -25.1757071
      },
      "EMA_50": 4065.845446,
      "EMA_200": 4273.741302,
      "Bollinger_Bands": {
        "upper": 4199.041673,
        "middle": 3985.722,
        "lower": 3772.402327,
        "bandwidth": 10.7
      },
      "Volume_SMA_20": 126835.9,
      "ATR": 104.21857143,
      "Williams_R": -88.59,
      "CCI": -208.92,
      "ADX": {
        "adx": 38.29,
        "di_plus": 15.1,
        "di_minus": 33.83
      },
      "OBV": -3190844.95,
      "Support_Resistance": {
        "resistance": 4217.6,
        "support": 3696.74,
        "resistance_distance_pct": 12.28,
        "support_distance_pct": 1.58
      },
      "Parabolic_SAR": {
        "sar": 4083.133274,
        "trend": -1,
        "is_bullish": false
      },
      "signal": "neutral",
      "signal_score": 0,
      "signal_details": [
        "Stoch_oversold",
        "MACD_bearish",
        "EMA_death_cross",
        "BB_oversold",
        "WilliamsR_oversold",
        "Strong_trend",
        "SAR_bearish"
      ]
    }
  },
  "updated_at": "2025-10-17T09:40:38Z"
}
