{
  "BTCUSDT": {
    "5m": {
      "price": 90538.72,
      "volume": 47.14,
      "RSI": 63.73,
      "Stoch_K": 98.59,
      "Stoch_D": 97.2,
      "MACD": {
        "line": 50.45005286,
        "signal": -59.33204571,
        "histogram": 109.78209857
      },
      "EMA_50": 90217.762755,
      "EMA_200": 91553.492721,
      "Bollinger_Bands": {
        "upper": 90549.178545,
        "middle": 89936.0215,
        "lower": 89322.864455,
        "bandwidth": 1.36
      },
      "Volume_SMA_20": 159.38,
      "ATR": 251.04214286,
      "Williams_R": -1.41,
      "CCI": 162.89,
      "ADX": {
        "adx": 21.6,
        "di_plus": 28.41,
        "di_minus": 18.31
      },
      "OBV": -6473.3,
      "Support_Resistance": {
        "resistance": 90555.88,
        "support": 89337.39,
        "resistance_distance_pct": 0.02,
        "support_distance_pct": 1.33
      },
      "Parabolic_SAR": {
        "sar": 89538.701042,
        "trend": 1,
        "is_bullish": true
      },
      "signal": "neutral",
      "signal_score": -2,
      "signal_details": [
        "Stoch_overbought",
        "MACD_bullish",
        "EMA_death_cross",
        "WilliamsR_overbought",
        "SAR_bullish",
        "Low_volume"
      ]
    },
    "15m": {
      "price": 90538.72,
      "volume": 599.65,
      "RSI": 49.85,
      "Stoch_K": 98.68,
      "Stoch_D": 64.16,
      "MACD": {
        "line": -376.22495466,
        "signal": -469.76701628,
        "histogram": 93.54206163
      },
      "EMA_50": 91227.572009,
      "EMA_200": 93462.30724,
      "Bollinger_Bands": {
        "upper": 90869.135498,
        "middle": 90174.4535,
        "lower": 89479.771502,
        "bandwidth": 1.54
      },
      "Volume_SMA_20": 672.09,
      "ATR": 471.64642857,
      "Williams_R": -1.32,
      "CCI": 46.46,
      "ADX": {
        "adx": 28.17,
        "di_plus": 15.58,
        "di_minus": 27.79
      },
      "OBV": -9001.68,
      "Support_Resistance": {
        "resistance": 91685.18,
        "support": 89253.78,
        "resistance_distance_pct": 1.27,
        "support_distance_pct": 1.42
      },
      "Parabolic_SAR": {
        "sar": 89337.39,
        "trend": 1,
        "is_bullish": true
      },
      "signal": "neutral",
      "signal_score": -1,
      "signal_details": [
        "MACD_bullish",
        "EMA_death_cross",
        "WilliamsR_overbought",
        "Strong_trend",
        "SAR_bullish"
      ]
    },
    "1h": {
      "price": 90529.68,
      "volume": 1946.39,
      "RSI": 33.48,
      "Stoch_K": 32.13,
      "Stoch_D": 19.53,
      "MACD": {
        "line": -1183.07833185,
        "signal": -1013.18417534,
        "histogram": -169.89415652
      },
      "EMA_50": 93537.92059,
      "EMA_200": 98136.22978,
      "Bollinger_Bands": {
        "upper": 95326.56394,
        "middle": 92186.13,
        "lower": 89045.69606,
        "bandwidth": 6.81
      },
      "Volume_SMA_20": 2334.69,
      "ATR": 980.37142857,
      "Williams_R": -67.87,
      "CCI": -102.61,
      "ADX": {
        "adx": 65.51,
        "di_plus": 6.49,
        "di_minus": 31.16
      },
      "OBV": -43740.23,
      "Support_Resistance": {
        "resistance": 96043,
        "support": 89253.78,
        "resistance_distance_pct": 6.09,
        "support_distance_pct": 1.41
      },
      "Parabolic_SAR": {
        "sar": 90756.273469,
        "trend": -1,
        "is_bullish": false
      },
      "signal": "sell",
      "signal_score": -4,
      "signal_details": [
        "MACD_bearish",
        "EMA_death_cross",
        "Strong_trend",
        "SAR_bearish"
      ]
    },
    "4h": {
      "price": 90529.68,
      "volume": 8208.45,
      "RSI": 27.21,
      "Stoch_K": 17.29,
      "Stoch_D": 17.38,
      "MACD": {
        "line": -1991.99525147,
        "signal": -1747.08531065,
        "histogram": -244.90994082
      },
      "EMA_50": 97782.859103,
      "EMA_200": 104404.568213,
      "Bollinger_Bands": {
        "upper": 98284.284576,
        "middle": 94633.26,
        "lower": 90982.235424,
        "bandwidth": 7.72
      },
      "Volume_SMA_20": 4853.73,
      "ATR": 1582.61785714,
      "Williams_R": -82.71,
      "CCI": -213.29,
      "ADX": {
        "adx": 63.64,
        "di_plus": 8.4,
        "di_minus": 37.81
      },
      "OBV": -71604.4,
      "Support_Resistance": {
        "resistance": 96846.68,
        "support": 89253.78,
        "resistance_distance_pct": 6.98,
        "support_distance_pct": 1.41
      },
      "Parabolic_SAR": {
        "sar": 95481.0752,
        "trend": -1,
        "is_bullish": false
      },
      "signal": "buy",
      "signal_score": 3,
      "signal_details": [
        "RSI_oversold",
        "Stoch_oversold",
        "MACD_bearish",
        "EMA_death_cross",
        "BB_oversold",
        "WilliamsR_oversold",
        "Strong_trend",
        "SAR_bearish",
        "High_volume"
      ]
    }
  },
  "ETHUSDT": {
    "5m": {
      "price": 3033.1,
      "volume": 517.78,
      "RSI": 63.9,
      "Stoch_K": 97.7,
      "Stoch_D": 97.44,
      "MACD": {
        "line": 4.7961489,
        "signal": -0.04961154,
        "histogram": 4.84576045
      },
      "EMA_50": 3004.128444,
      "EMA_200": 3029.913636,
      "Bollinger_Bands": {
        "upper": 3032.611269,
        "middle": 3001.0575,
        "lower": 2969.503731,
        "bandwidth": 2.1
      },
      "Volume_SMA_20": 2678.58,
      "ATR": 12.70642857,
      "Williams_R": -2.3,
      "CCI": 175.74,
      "ADX": {
        "adx": 22.72,
        "di_plus": 31.97,
        "di_minus": 20.14
      },
      "OBV": -81134.96,
      "Support_Resistance": {
        "resistance": 3034.5,
        "support": 2973.53,
        "resistance_distance_pct": 0.05,
        "support_distance_pct": 1.96
      },
      "Parabolic_SAR": {
        "sar": 2983.753666,
        "trend": 1,
        "is_bullish": true
      },
      "signal": "sell",
      "signal_score": -3,
      "signal_details": [
        "Stoch_overbought",
        "MACD_bullish",
        "EMA_death_cross",
        "BB_overbought",
        "WilliamsR_overbought",
        "SAR_bullish",
        "Low_volume"
      ]
    },
    "15m": {
      "price": 3033.1,
      "volume": 7468.64,
      "RSI": 56.74,
      "Stoch_K": 98.17,
      "Stoch_D": 77.48,
      "MACD": {
        "line": -1.95886548,
        "signal": -5.21403709,
        "histogram": 3.25517161
      },
      "EMA_50": 3022.974732,
      "EMA_200": 3098.36833,
      "Bollinger_Bands": {
        "upper": 3036.083954,
        "middle": 2999.608,
        "lower": 2963.132046,
        "bandwidth": 2.43
      },
      "Volume_SMA_20": 11060.47,
      "ATR": 25.32642857,
      "Williams_R": -1.83,
      "CCI": 131.9,
      "ADX": {
        "adx": 16.06,
        "di_plus": 16.82,
        "di_minus": 23.26
      },
      "OBV": -221055.3,
      "Support_Resistance": {
        "resistance": 3044.67,
        "support": 2946.56,
        "resistance_distance_pct": 0.38,
        "support_distance_pct": 2.85
      },
      "Parabolic_SAR": {
        "sar": 2946.56,
        "trend": 1,
        "is_bullish": true
      },
      "signal": "neutral",
      "signal_score": 0,
      "signal_details": [
        "MACD_bullish",
        "EMA_death_cross",
        "WilliamsR_overbought",
        "SAR_bullish"
      ]
    },
    "1h": {
      "price": 3033.1,
      "volume": 22329.72,
      "RSI": 45.18,
      "Stoch_K": 64.35,
      "Stoch_D": 40.14,
      "MACD": {
        "line": -34.16100606,
        "signal": -35.09799151,
        "histogram": 0.93698545
      },
      "EMA_50": 3098.143691,
      "EMA_200": 3274.173103,
      "Bollinger_Bands": {
        "upper": 3164.959947,
        "middle": 3047.438,
        "lower": 2929.916053,
        "bandwidth": 7.71
      },
      "Volume_SMA_20": 43792.9,
      "ATR": 52.19714286,
      "Williams_R": -35.65,
      "CCI": -41.88,
      "ADX": {
        "adx": 47.61,
        "di_plus": 8.29,
        "di_minus": 23.35
      },
      "OBV": -602193.32,
      "Support_Resistance": {
        "resistance": 3210.88,
        "support": 2946.56,
        "resistance_distance_pct": 5.86,
        "support_distance_pct": 2.85
      },
      "Parabolic_SAR": {
        "sar": 2946.56,
        "trend": 1,
        "is_bullish": true
      },
      "signal": "neutral",
      "signal_score": 0,
      "signal_details": [
        "MACD_bullish",
        "EMA_death_cross",
        "Strong_trend",
        "SAR_bullish"
      ]
    },
    "4h": {
      "price": 3033.1,
      "volume": 133929.87,
      "RSI": 37.92,
      "Stoch_K": 28.61,
      "Stoch_D": 26.36,
      "MACD": {
        "line": -67.99184453,
        "signal": -63.0765064,
        "histogram": -4.91533813
      },
      "EMA_50": 3256.454368,
      "EMA_200": 3585.470566,
      "Bollinger_Bands": {
        "upper": 3274.540798,
        "middle": 3135.7,
        "lower": 2996.859202,
        "bandwidth": 8.86
      },
      "Volume_SMA_20": 99732.74,
      "ATR": 88.21357143,
      "Williams_R": -71.39,
      "CCI": -140.63,
      "ADX": {
        "adx": 40.92,
        "di_plus": 12.43,
        "di_minus": 29.66
      },
      "OBV": -722355.14,
      "Support_Resistance": {
        "resistance": 3249,
        "support": 2946.56,
        "resistance_distance_pct": 7.12,
        "support_distance_pct": 2.85
      },
      "Parabolic_SAR": {
        "sar": 3192.326384,
        "trend": -1,
        "is_bullish": false
      },
      "signal": "sell",
      "signal_score": -4,
      "signal_details": [
        "MACD_bearish",
        "EMA_death_cross",
        "Strong_trend",
        "SAR_bearish"
      ]
    }
  },
  "updated_at": "2025-11-18T07:40:48Z"
}
