{
  "BTCUSDT": {
    "5m": {
      "price": 103000.99,
      "volume": 164.69,
      "RSI": 31.18,
      "Stoch_K": 20.04,
      "Stoch_D": 15.43,
      "MACD": {
        "line": -164.58495928,
        "signal": -147.87817537,
        "histogram": -16.7067839
      },
      "EMA_50": 103792.404966,
      "EMA_200": 104804.923333,
      "Bollinger_Bands": {
        "upper": 103771.216274,
        "middle": 103435.7805,
        "lower": 103100.344726,
        "bandwidth": 0.65
      },
      "Volume_SMA_20": 56.03,
      "ATR": 186.53785714,
      "Williams_R": -79.96,
      "CCI": -272.38,
      "ADX": {
        "adx": 56.83,
        "di_plus": 10.54,
        "di_minus": 38.28
      },
      "OBV": -4352.84,
      "Support_Resistance": {
        "resistance": 103730,
        "support": 102840.22,
        "resistance_distance_pct": 0.71,
        "support_distance_pct": 0.16
      },
      "Parabolic_SAR": {
        "sar": 103630.2458,
        "trend": -1,
        "is_bullish": false
      },
      "signal": "neutral",
      "signal_score": -2,
      "signal_details": [
        "MACD_bearish",
        "EMA_death_cross",
        "BB_oversold",
        "Strong_trend",
        "SAR_bearish",
        "High_volume"
      ]
    },
    "15m": {
      "price": 103000.99,
      "volume": 287.98,
      "RSI": 27.75,
      "Stoch_K": 8.81,
      "Stoch_D": 16.88,
      "MACD": {
        "line": -449.18253274,
        "signal": -408.87020404,
        "histogram": -40.31232871
      },
      "EMA_50": 104528.147137,
      "EMA_200": 105035.34023,
      "Bollinger_Bands": {
        "upper": 104902.915325,
        "middle": 103910.453,
        "lower": 102917.990675,
        "bandwidth": 1.91
      },
      "Volume_SMA_20": 465.9,
      "ATR": 436.13,
      "Williams_R": -91.19,
      "CCI": -121.81,
      "ADX": {
        "adx": 65.36,
        "di_plus": 6.7,
        "di_minus": 31.96
      },
      "OBV": -6053.29,
      "Support_Resistance": {
        "resistance": 104788,
        "support": 102840.22,
        "resistance_distance_pct": 1.73,
        "support_distance_pct": 0.16
      },
      "Parabolic_SAR": {
        "sar": 103637.27,
        "trend": -1,
        "is_bullish": false
      },
      "signal": "neutral",
      "signal_score": 1,
      "signal_details": [
        "RSI_oversold",
        "Stoch_oversold",
        "MACD_bearish",
        "EMA_death_cross",
        "WilliamsR_oversold",
        "Strong_trend",
        "SAR_bearish"
      ]
    },
    "1h": {
      "price": 103001,
      "volume": 520.52,
      "RSI": 30.17,
      "Stoch_K": 4.34,
      "Stoch_D": 5.79,
      "MACD": {
        "line": -506.83087899,
        "signal": -226.15266234,
        "histogram": -280.67821665
      },
      "EMA_50": 104776.368422,
      "EMA_200": 104254.817633,
      "Bollinger_Bands": {
        "upper": 107115.703724,
        "middle": 105122.055,
        "lower": 103128.406276,
        "bandwidth": 3.79
      },
      "Volume_SMA_20": 1048.93,
      "ATR": 686.10857143,
      "Williams_R": -95.66,
      "CCI": -175.75,
      "ADX": {
        "adx": 44.74,
        "di_plus": 11.73,
        "di_minus": 30.71
      },
      "OBV": 2785.48,
      "Support_Resistance": {
        "resistance": 107500,
        "support": 102840.22,
        "resistance_distance_pct": 4.37,
        "support_distance_pct": 0.16
      },
      "Parabolic_SAR": {
        "sar": 105219.198587,
        "trend": -1,
        "is_bullish": false
      },
      "signal": "neutral",
      "signal_score": 2,
      "signal_details": [
        "Stoch_oversold",
        "MACD_bearish",
        "EMA_golden_cross",
        "BB_oversold",
        "WilliamsR_oversold",
        "Strong_trend",
        "SAR_bearish",
        "Low_volume"
      ]
    },
    "4h": {
      "price": 103001,
      "volume": 1184.71,
      "RSI": 43.52,
      "Stoch_K": 17.44,
      "Stoch_D": 37.86,
      "MACD": {
        "line": 294.54262975,
        "signal": 436.35811942,
        "histogram": -141.81548967
      },
      "EMA_50": 104699.951516,
      "EMA_200": 109413.10514,
      "Bollinger_Bands": {
        "upper": 107608.212831,
        "middle": 104186.7345,
        "lower": 100765.256169,
        "bandwidth": 6.57
      },
      "Volume_SMA_20": 3261.08,
      "ATR": 1494.10714286,
      "Williams_R": -82.56,
      "CCI": -42.61,
      "ADX": {
        "adx": 9.5,
        "di_plus": 20.17,
        "di_minus": 24.41
      },
      "OBV": -77388.56,
      "Support_Resistance": {
        "resistance": 107500,
        "support": 101400,
        "resistance_distance_pct": 4.37,
        "support_distance_pct": 1.55
      },
      "Parabolic_SAR": {
        "sar": 107413.4066,
        "trend": -1,
        "is_bullish": false
      },
      "signal": "neutral",
      "signal_score": -2,
      "signal_details": [
        "MACD_bearish",
        "EMA_death_cross",
        "WilliamsR_oversold",
        "SAR_bearish",
        "Low_volume"
      ]
    }
  },
  "ETHUSDT": {
    "5m": {
      "price": 3455.59,
      "volume": 4486.26,
      "RSI": 33.12,
      "Stoch_K": 17.54,
      "Stoch_D": 6.83,
      "MACD": {
        "line": -9.19590851,
        "signal": -7.37454983,
        "histogram": -1.82135868
      },
      "EMA_50": 3499.225624,
      "EMA_200": 3542.435447,
      "Bollinger_Bands": {
        "upper": 3503.178129,
        "middle": 3481.182,
        "lower": 3459.185871,
        "bandwidth": 1.26
      },
      "Volume_SMA_20": 2396.55,
      "ATR": 11.48642857,
      "Williams_R": -82.46,
      "CCI": -238.27,
      "ADX": {
        "adx": 47.51,
        "di_plus": 13.09,
        "di_minus": 36.77
      },
      "OBV": -31591.33,
      "Support_Resistance": {
        "resistance": 3500.59,
        "support": 3446.02,
        "resistance_distance_pct": 1.3,
        "support_distance_pct": 0.28
      },
      "Parabolic_SAR": {
        "sar": 3498.265216,
        "trend": -1,
        "is_bullish": false
      },
      "signal": "neutral",
      "signal_score": 1,
      "signal_details": [
        "Stoch_oversold",
        "MACD_bearish",
        "EMA_death_cross",
        "BB_oversold",
        "WilliamsR_oversold",
        "Strong_trend",
        "SAR_bearish",
        "High_volume"
      ]
    },
    "15m": {
      "price": 3455.59,
      "volume": 10020.04,
      "RSI": 29.49,
      "Stoch_K": 9.42,
      "Stoch_D": 15.92,
      "MACD": {
        "line": -22.37896357,
        "signal": -19.7716551,
        "histogram": -2.60730847
      },
      "EMA_50": 3531.240807,
      "EMA_200": 3554.159574,
      "Bollinger_Bands": {
        "upper": 3568.941447,
        "middle": 3507.208,
        "lower": 3445.474553,
        "bandwidth": 3.52
      },
      "Volume_SMA_20": 9309.41,
      "ATR": 26.06428571,
      "Williams_R": -90.58,
      "CCI": -119.46,
      "ADX": {
        "adx": 55.27,
        "di_plus": 8.72,
        "di_minus": 30.27
      },
      "OBV": 70595.75,
      "Support_Resistance": {
        "resistance": 3573.43,
        "support": 3446.02,
        "resistance_distance_pct": 3.41,
        "support_distance_pct": 0.28
      },
      "Parabolic_SAR": {
        "sar": 3500.59,
        "trend": -1,
        "is_bullish": false
      },
      "signal": "neutral",
      "signal_score": 1,
      "signal_details": [
        "RSI_oversold",
        "Stoch_oversold",
        "MACD_bearish",
        "EMA_death_cross",
        "WilliamsR_oversold",
        "Strong_trend",
        "SAR_bearish"
      ]
    },
    "1h": {
      "price": 3456.27,
      "volume": 17492.06,
      "RSI": 32.1,
      "Stoch_K": 6.23,
      "Stoch_D": 8.8,
      "MACD": {
        "line": -19.96971696,
        "signal": -8.0669847,
        "histogram": -11.90273227
      },
      "EMA_50": 3536.914424,
      "EMA_200": 3505.247623,
      "Bollinger_Bands": {
        "upper": 3630.401407,
        "middle": 3551.9225,
        "lower": 3473.443593,
        "bandwidth": 4.42
      },
      "Volume_SMA_20": 28453.66,
      "ATR": 37.91428571,
      "Williams_R": -93.77,
      "CCI": -214.16,
      "ADX": {
        "adx": 36.32,
        "di_plus": 12.49,
        "di_minus": 26.74
      },
      "OBV": -183528.89,
      "Support_Resistance": {
        "resistance": 3648.27,
        "support": 3446.02,
        "resistance_distance_pct": 5.56,
        "support_distance_pct": 0.3
      },
      "Parabolic_SAR": {
        "sar": 3573.946061,
        "trend": -1,
        "is_bullish": false
      },
      "signal": "neutral",
      "signal_score": 2,
      "signal_details": [
        "Stoch_oversold",
        "MACD_bearish",
        "EMA_golden_cross",
        "BB_oversold",
        "WilliamsR_oversold",
        "Strong_trend",
        "SAR_bearish"
      ]
    },
    "4h": {
      "price": 3456.27,
      "volume": 49640.79,
      "RSI": 45.15,
      "Stoch_K": 13.5,
      "Stoch_D": 39.94,
      "MACD": {
        "line": 18.30366052,
        "signal": 25.73671281,
        "histogram": -7.43305228
      },
      "EMA_50": 3533.699283,
      "EMA_200": 3801.900354,
      "Bollinger_Bands": {
        "upper": 3681.404248,
        "middle": 3511.442,
        "lower": 3341.479752,
        "bandwidth": 9.68
      },
      "Volume_SMA_20": 87105.97,
      "ATR": 79.10928571,
      "Williams_R": -86.5,
      "CCI": -38.87,
      "ADX": {
        "adx": 9.33,
        "di_plus": 19.47,
        "di_minus": 23.48
      },
      "OBV": -954017.62,
      "Support_Resistance": {
        "resistance": 3658.98,
        "support": 3355.58,
        "resistance_distance_pct": 5.86,
        "support_distance_pct": 2.91
      },
      "Parabolic_SAR": {
        "sar": 3655.1446,
        "trend": -1,
        "is_bullish": false
      },
      "signal": "neutral",
      "signal_score": -2,
      "signal_details": [
        "MACD_bearish",
        "EMA_death_cross",
        "WilliamsR_oversold",
        "SAR_bearish"
      ]
    }
  },
  "updated_at": "2025-11-11T17:42:09Z"
}
