{
  "BTCUSDT": {
    "5m": {
      "price": 113248.06,
      "volume": 42.16,
      "RSI": 60.59,
      "Stoch_K": 95.74,
      "Stoch_D": 90.73,
      "MACD": {
        "line": 49.73563125,
        "signal": 30.93885141,
        "histogram": 18.79677984
      },
      "EMA_50": 112997.927557,
      "EMA_200": 112625.575072,
      "Bollinger_Bands": {
        "upper": 113270.764154,
        "middle": 113077.432,
        "lower": 112884.099846,
        "bandwidth": 0.34
      },
      "Volume_SMA_20": 51.06,
      "ATR": 131.39928571,
      "Williams_R": -4.26,
      "CCI": 180.39,
      "ADX": {
        "adx": 8.47,
        "di_plus": 22.9,
        "di_minus": 19.33
      },
      "OBV": -628.73,
      "Support_Resistance": {
        "resistance": 113267.62,
        "support": 112808,
        "resistance_distance_pct": 0.02,
        "support_distance_pct": 0.39
      },
      "Parabolic_SAR": {
        "sar": 112877.253542,
        "trend": 1,
        "is_bullish": true
      },
      "signal": "neutral",
      "signal_score": 0,
      "signal_details": [
        "Stoch_overbought",
        "MACD_bullish",
        "EMA_golden_cross",
        "WilliamsR_overbought",
        "SAR_bullish"
      ]
    },
    "15m": {
      "price": 113248.06,
      "volume": 142.27,
      "RSI": 64,
      "Stoch_K": 95.74,
      "Stoch_D": 86.88,
      "MACD": {
        "line": 143.39255582,
        "signal": 146.0401939,
        "histogram": -2.64763808
      },
      "EMA_50": 112733.314741,
      "EMA_200": 112581.863247,
      "Bollinger_Bands": {
        "upper": 113288.483916,
        "middle": 112995.758,
        "lower": 112703.032084,
        "bandwidth": 0.52
      },
      "Volume_SMA_20": 115.73,
      "ATR": 169.69642857,
      "Williams_R": -4.26,
      "CCI": 144.91,
      "ADX": {
        "adx": 16.16,
        "di_plus": 20.17,
        "di_minus": 14.56
      },
      "OBV": 200.47,
      "Support_Resistance": {
        "resistance": 113267.62,
        "support": 112668.51,
        "resistance_distance_pct": 0.02,
        "support_distance_pct": 0.51
      },
      "Parabolic_SAR": {
        "sar": 112808,
        "trend": 1,
        "is_bullish": true
      },
      "signal": "neutral",
      "signal_score": -2,
      "signal_details": [
        "Stoch_overbought",
        "MACD_bearish",
        "EMA_golden_cross",
        "WilliamsR_overbought",
        "SAR_bullish"
      ]
    },
    "1h": {
      "price": 113248.06,
      "volume": 453,
      "RSI": 60.87,
      "Stoch_K": 99.12,
      "Stoch_D": 92.17,
      "MACD": {
        "line": 126.68205728,
        "signal": 11.15841505,
        "histogram": 115.52364223
      },
      "EMA_50": 112866.17968,
      "EMA_200": 114461.670363,
      "Bollinger_Bands": {
        "upper": 113336.189907,
        "middle": 112444.3995,
        "lower": 111552.609093,
        "bandwidth": 1.59
      },
      "Volume_SMA_20": 521.57,
      "ATR": 432.195,
      "Williams_R": -0.88,
      "CCI": 121.5,
      "ADX": {
        "adx": 10.18,
        "di_plus": 16.71,
        "di_minus": 20.49
      },
      "OBV": -14124.11,
      "Support_Resistance": {
        "resistance": 113267.62,
        "support": 111042.66,
        "resistance_distance_pct": 0.02,
        "support_distance_pct": 1.95
      },
      "Parabolic_SAR": {
        "sar": 111961.994633,
        "trend": 1,
        "is_bullish": true
      },
      "signal": "neutral",
      "signal_score": -2,
      "signal_details": [
        "Stoch_overbought",
        "MACD_bullish",
        "EMA_death_cross",
        "WilliamsR_overbought",
        "SAR_bullish"
      ]
    },
    "4h": {
      "price": 113248.06,
      "volume": 1304.12,
      "RSI": 46.75,
      "Stoch_K": 92.27,
      "Stoch_D": 60.96,
      "MACD": {
        "line": -743.02076814,
        "signal": -849.35281883,
        "histogram": 106.33205069
      },
      "EMA_50": 114224.212572,
      "EMA_200": 113512.312962,
      "Bollinger_Bands": {
        "upper": 115786.910078,
        "middle": 113248.509,
        "lower": 110710.107922,
        "bandwidth": 4.48
      },
      "Volume_SMA_20": 2224.71,
      "ATR": 981.71285714,
      "Williams_R": -7.73,
      "CCI": -8.58,
      "ADX": {
        "adx": 41.41,
        "di_plus": 11.8,
        "di_minus": 28.48
      },
      "OBV": -43879.24,
      "Support_Resistance": {
        "resistance": 115819.06,
        "support": 111042.66,
        "resistance_distance_pct": 2.27,
        "support_distance_pct": 1.95
      },
      "Parabolic_SAR": {
        "sar": 111042.66,
        "trend": 1,
        "is_bullish": true
      },
      "signal": "neutral",
      "signal_score": 1,
      "signal_details": [
        "MACD_bullish",
        "EMA_golden_cross",
        "WilliamsR_overbought",
        "Strong_trend",
        "SAR_bullish"
      ]
    }
  },
  "ETHUSDT": {
    "5m": {
      "price": 4176.3,
      "volume": 354.47,
      "RSI": 53.38,
      "Stoch_K": 82.81,
      "Stoch_D": 79.35,
      "MACD": {
        "line": -1.33750766,
        "signal": -2.7335825,
        "histogram": 1.39607485
      },
      "EMA_50": 4174.473892,
      "EMA_200": 4174.0104,
      "Bollinger_Bands": {
        "upper": 4184.572508,
        "middle": 4170.8315,
        "lower": 4157.090492,
        "bandwidth": 0.66
      },
      "Volume_SMA_20": 1706.77,
      "ATR": 10.07714286,
      "Williams_R": -17.19,
      "CCI": 62.53,
      "ADX": {
        "adx": 12.19,
        "di_plus": 17.66,
        "di_minus": 22.56
      },
      "OBV": -45278.3,
      "Support_Resistance": {
        "resistance": 4185.51,
        "support": 4145.96,
        "resistance_distance_pct": 0.22,
        "support_distance_pct": 0.73
      },
      "Parabolic_SAR": {
        "sar": 4152.355505,
        "trend": 1,
        "is_bullish": true
      },
      "signal": "neutral",
      "signal_score": 2,
      "signal_details": [
        "MACD_bullish",
        "EMA_golden_cross",
        "WilliamsR_overbought",
        "SAR_bullish",
        "Low_volume"
      ]
    },
    "15m": {
      "price": 4176.3,
      "volume": 2089.13,
      "RSI": 51.12,
      "Stoch_K": 58.1,
      "Stoch_D": 50.62,
      "MACD": {
        "line": -0.83748614,
        "signal": 0.55418702,
        "histogram": -1.39167316
      },
      "EMA_50": 4173.542403,
      "EMA_200": 4178.135651,
      "Bollinger_Bands": {
        "upper": 4194.65771,
        "middle": 4177.185,
        "lower": 4159.71229,
        "bandwidth": 0.84
      },
      "Volume_SMA_20": 3581.56,
      "ATR": 12.78785714,
      "Williams_R": -41.9,
      "CCI": -18.52,
      "ADX": {
        "adx": 21.77,
        "di_plus": 15.23,
        "di_minus": 23.7
      },
      "OBV": -43517.54,
      "Support_Resistance": {
        "resistance": 4198.34,
        "support": 4145.96,
        "resistance_distance_pct": 0.53,
        "support_distance_pct": 0.73
      },
      "Parabolic_SAR": {
        "sar": 4191.624056,
        "trend": -1,
        "is_bullish": false
      },
      "signal": "sell",
      "signal_score": -3,
      "signal_details": [
        "MACD_bearish",
        "EMA_death_cross",
        "SAR_bearish"
      ]
    },
    "1h": {
      "price": 4176.3,
      "volume": 11082.14,
      "RSI": 49.61,
      "Stoch_K": 82.31,
      "Stoch_D": 76.39,
      "MACD": {
        "line": -4.2791179,
        "signal": -5.84960132,
        "histogram": 1.57048342
      },
      "EMA_50": 4203.056654,
      "EMA_200": 4356.3504,
      "Bollinger_Bands": {
        "upper": 4198.051443,
        "middle": 4171.785,
        "lower": 4145.518557,
        "bandwidth": 1.26
      },
      "Volume_SMA_20": 14011.28,
      "ATR": 29.58285714,
      "Williams_R": -17.69,
      "CCI": -9.39,
      "ADX": {
        "adx": 37.3,
        "di_plus": 11.56,
        "di_minus": 25.31
      },
      "OBV": -437569.07,
      "Support_Resistance": {
        "resistance": 4198.34,
        "support": 4073.74,
        "resistance_distance_pct": 0.53,
        "support_distance_pct": 2.46
      },
      "Parabolic_SAR": {
        "sar": 4091.976125,
        "trend": 1,
        "is_bullish": true
      },
      "signal": "neutral",
      "signal_score": -1,
      "signal_details": [
        "MACD_bullish",
        "EMA_death_cross",
        "WilliamsR_overbought",
        "Strong_trend",
        "SAR_bullish"
      ]
    },
    "4h": {
      "price": 4176.3,
      "volume": 45686.38,
      "RSI": 33.87,
      "Stoch_K": 66.04,
      "Stoch_D": 46.11,
      "MACD": {
        "line": -75.43018701,
        "signal": -80.80069645,
        "histogram": 5.37050943
      },
      "EMA_50": 4351.322244,
      "EMA_200": 4407.099141,
      "Bollinger_Bands": {
        "upper": 4480.363639,
        "middle": 4241.5275,
        "lower": 4002.691361,
        "bandwidth": 11.26
      },
      "Volume_SMA_20": 68581.44,
      "ATR": 64.00142857,
      "Williams_R": -33.96,
      "CCI": -47.16,
      "ADX": {
        "adx": 64.52,
        "di_plus": 7.12,
        "di_minus": 33.03
      },
      "OBV": -235803.7,
      "Support_Resistance": {
        "resistance": 4498.16,
        "support": 4073.74,
        "resistance_distance_pct": 7.71,
        "support_distance_pct": 2.46
      },
      "Parabolic_SAR": {
        "sar": 4212.466827,
        "trend": -1,
        "is_bullish": false
      },
      "signal": "neutral",
      "signal_score": -2,
      "signal_details": [
        "MACD_bullish",
        "EMA_death_cross",
        "Strong_trend",
        "SAR_bearish"
      ]
    }
  },
  "updated_at": "2025-09-24T14:41:39Z"
}
