{
  "BTCUSDT": {
    "5m": {
      "price": 69226.54,
      "volume": 55.09,
      "RSI": 46.9,
      "Stoch_K": 55.8,
      "Stoch_D": 44.42,
      "MACD": {
        "line": -108.89749159,
        "signal": -90.98987886,
        "histogram": -17.90761273
      },
      "EMA_50": 69336.046741,
      "EMA_200": 69095.35752,
      "Bollinger_Bands": {
        "upper": 69765.718099,
        "middle": 69314.952,
        "lower": 68864.185901,
        "bandwidth": 1.3
      },
      "Volume_SMA_20": 51.74,
      "ATR": 163.365,
      "Williams_R": -44.2,
      "CCI": -32.85,
      "ADX": {
        "adx": 9.4,
        "di_plus": 23.72,
        "di_minus": 28.64
      },
      "OBV": 582.31,
      "Support_Resistance": {
        "resistance": 69727.86,
        "support": 68787.34,
        "resistance_distance_pct": 0.72,
        "support_distance_pct": 0.63
      },
      "Parabolic_SAR": {
        "sar": 68787.34,
        "trend": 1,
        "is_bullish": true
      },
      "signal": "neutral",
      "signal_score": 1,
      "signal_details": [
        "MACD_bearish",
        "EMA_golden_cross",
        "SAR_bullish"
      ]
    },
    "15m": {
      "price": 69226.54,
      "volume": 148.58,
      "RSI": 47.27,
      "Stoch_K": 46.65,
      "Stoch_D": 32.7,
      "MACD": {
        "line": 10.17538353,
        "signal": 70.35282085,
        "histogram": -60.17743732
      },
      "EMA_50": 69253.473909,
      "EMA_200": 68046.782394,
      "Bollinger_Bands": {
        "upper": 69713.171221,
        "middle": 69410.2165,
        "lower": 69107.261779,
        "bandwidth": 0.87
      },
      "Volume_SMA_20": 125.4,
      "ATR": 239.985,
      "Williams_R": -53.35,
      "CCI": -133.74,
      "ADX": {
        "adx": 8.14,
        "di_plus": 19.64,
        "di_minus": 23.12
      },
      "OBV": 15540.81,
      "Support_Resistance": {
        "resistance": 69728.83,
        "support": 68787.34,
        "resistance_distance_pct": 0.73,
        "support_distance_pct": 0.63
      },
      "Parabolic_SAR": {
        "sar": 69833.704096,
        "trend": -1,
        "is_bullish": false
      },
      "signal": "neutral",
      "signal_score": -1,
      "signal_details": [
        "MACD_bearish",
        "EMA_golden_cross",
        "SAR_bearish"
      ]
    },
    "1h": {
      "price": 69226.54,
      "volume": 565.22,
      "RSI": 51.23,
      "Stoch_K": 68.01,
      "Stoch_D": 74.13,
      "MACD": {
        "line": 145.29503779,
        "signal": 139.11624953,
        "histogram": 6.17878827
      },
      "EMA_50": 69200.550262,
      "EMA_200": 73657.617853,
      "Bollinger_Bands": {
        "upper": 70456.974545,
        "middle": 69054.2235,
        "lower": 67651.472455,
        "bandwidth": 4.06
      },
      "Volume_SMA_20": 1971.68,
      "ATR": 761.42857143,
      "Williams_R": -31.99,
      "CCI": 5.51,
      "ADX": {
        "adx": 3.56,
        "di_plus": 22.25,
        "di_minus": 20.72
      },
      "OBV": -89197.02,
      "Support_Resistance": {
        "resistance": 71690.07,
        "support": 67300,
        "resistance_distance_pct": 3.56,
        "support_distance_pct": 2.78
      },
      "Parabolic_SAR": {
        "sar": 67348.5572,
        "trend": 1,
        "is_bullish": true
      },
      "signal": "neutral",
      "signal_score": 1,
      "signal_details": [
        "MACD_bullish",
        "EMA_death_cross",
        "SAR_bullish",
        "Low_volume"
      ]
    },
    "4h": {
      "price": 69226.54,
      "volume": 1789.02,
      "RSI": 43.82,
      "Stoch_K": 78.51,
      "Stoch_D": 78.23,
      "MACD": {
        "line": -1673.69608582,
        "signal": -2260.76561445,
        "histogram": 587.06952863
      },
      "EMA_50": 74196.808997,
      "EMA_200": 84408.952682,
      "Bollinger_Bands": {
        "upper": 74446.084428,
        "middle": 68768.7975,
        "lower": 63091.510572,
        "bandwidth": 16.51
      },
      "Volume_SMA_20": 13152.92,
      "ATR": 2663.68214286,
      "Williams_R": -21.49,
      "CCI": 12.07,
      "ADX": {
        "adx": 30.55,
        "di_plus": 14.95,
        "di_minus": 28.11
      },
      "OBV": -120525.06,
      "Support_Resistance": {
        "resistance": 74249.83,
        "support": 60000,
        "resistance_distance_pct": 7.26,
        "support_distance_pct": 13.33
      },
      "Parabolic_SAR": {
        "sar": 64083.535279,
        "trend": 1,
        "is_bullish": true
      },
      "signal": "neutral",
      "signal_score": 0,
      "signal_details": [
        "MACD_bullish",
        "EMA_death_cross",
        "Strong_trend",
        "SAR_bullish",
        "Low_volume"
      ]
    }
  },
  "ETHUSDT": {
    "5m": {
      "price": 2087.2,
      "volume": 1165.22,
      "RSI": 46.39,
      "Stoch_K": 54.22,
      "Stoch_D": 44.94,
      "MACD": {
        "line": -3.9117395,
        "signal": -3.4367849,
        "histogram": -0.4749546
      },
      "EMA_50": 2089.560484,
      "EMA_200": 2066.032172,
      "Bollinger_Bands": {
        "upper": 2105.073124,
        "middle": 2090.1045,
        "lower": 2075.135876,
        "bandwidth": 1.43
      },
      "Volume_SMA_20": 1203.78,
      "ATR": 6.07357143,
      "Williams_R": -45.78,
      "CCI": -32.8,
      "ADX": {
        "adx": 9.23,
        "di_plus": 20.31,
        "di_minus": 24.45
      },
      "OBV": -134076.84,
      "Support_Resistance": {
        "resistance": 2107.56,
        "support": 2073,
        "resistance_distance_pct": 0.98,
        "support_distance_pct": 0.68
      },
      "Parabolic_SAR": {
        "sar": 2090.149532,
        "trend": -1,
        "is_bullish": false
      },
      "signal": "neutral",
      "signal_score": -1,
      "signal_details": [
        "MACD_bearish",
        "EMA_golden_cross",
        "SAR_bearish"
      ]
    },
    "15m": {
      "price": 2087.2,
      "volume": 3543.78,
      "RSI": 52.03,
      "Stoch_K": 33.81,
      "Stoch_D": 24.11,
      "MACD": {
        "line": 5.5933832,
        "signal": 9.45430252,
        "histogram": -3.86091931
      },
      "EMA_50": 2073.175459,
      "EMA_200": 2011.092545,
      "Bollinger_Bands": {
        "upper": 2109.194672,
        "middle": 2094.746,
        "lower": 2080.297328,
        "bandwidth": 1.38
      },
      "Volume_SMA_20": 4973.27,
      "ATR": 11.11357143,
      "Williams_R": -66.19,
      "CCI": -102,
      "ADX": {
        "adx": 8.39,
        "di_plus": 20.96,
        "di_minus": 17.72
      },
      "OBV": 648791.63,
      "Support_Resistance": {
        "resistance": 2115,
        "support": 2073,
        "resistance_distance_pct": 1.33,
        "support_distance_pct": 0.68
      },
      "Parabolic_SAR": {
        "sar": 2057.995792,
        "trend": 1,
        "is_bullish": true
      },
      "signal": "neutral",
      "signal_score": 1,
      "signal_details": [
        "MACD_bearish",
        "EMA_golden_cross",
        "SAR_bullish"
      ]
    },
    "1h": {
      "price": 2087.2,
      "volume": 11493.78,
      "RSI": 58.83,
      "Stoch_K": 71.75,
      "Stoch_D": 75.74,
      "MACD": {
        "line": 19.15489802,
        "signal": 15.95954583,
        "histogram": 3.19535219
      },
      "EMA_50": 2048.369577,
      "EMA_200": 2223.125676,
      "Bollinger_Bands": {
        "upper": 2121.022617,
        "middle": 2057.304,
        "lower": 1993.585383,
        "bandwidth": 6.19
      },
      "Volume_SMA_20": 50698.07,
      "ATR": 36.36428571,
      "Williams_R": -28.25,
      "CCI": 59.48,
      "ADX": {
        "adx": 30.89,
        "di_plus": 28.73,
        "di_minus": 15.17
      },
      "OBV": -2444092.86,
      "Support_Resistance": {
        "resistance": 2121.7,
        "support": 1994.57,
        "resistance_distance_pct": 1.65,
        "support_distance_pct": 4.44
      },
      "Parabolic_SAR": {
        "sar": 2011.335201,
        "trend": 1,
        "is_bullish": true
      },
      "signal": "neutral",
      "signal_score": 2,
      "signal_details": [
        "MACD_bullish",
        "EMA_death_cross",
        "Strong_trend",
        "SAR_bullish",
        "Low_volume"
      ]
    },
    "4h": {
      "price": 2087.2,
      "volume": 70843.3,
      "RSI": 48,
      "Stoch_K": 90.77,
      "Stoch_D": 86.15,
      "MACD": {
        "line": -53.05881826,
        "signal": -82.41446899,
        "histogram": 29.35565073
      },
      "EMA_50": 2247.704479,
      "EMA_200": 2743.163611,
      "Bollinger_Bands": {
        "upper": 2209.810166,
        "middle": 2026.3035,
        "lower": 1842.796834,
        "bandwidth": 18.11
      },
      "Volume_SMA_20": 291491.64,
      "ATR": 91.76071429,
      "Williams_R": -9.23,
      "CCI": 59.56,
      "ADX": {
        "adx": 16.38,
        "di_plus": 16.86,
        "di_minus": 23.47
      },
      "OBV": -2201382.33,
      "Support_Resistance": {
        "resistance": 2194.71,
        "support": 1747.8,
        "resistance_distance_pct": 5.15,
        "support_distance_pct": 16.26
      },
      "Parabolic_SAR": {
        "sar": 1898.957906,
        "trend": 1,
        "is_bullish": true
      },
      "signal": "neutral",
      "signal_score": -2,
      "signal_details": [
        "Stoch_overbought",
        "MACD_bullish",
        "EMA_death_cross",
        "WilliamsR_overbought",
        "SAR_bullish",
        "Low_volume"
      ]
    }
  },
  "updated_at": "2026-02-07T23:38:57Z"
}
